instalabel/__init__.py
instalabel/config.py
instalabel/client/__init__.py
instalabel/client/api_client.py
instalabel/client/api_response.py
instalabel/client/configuration.py
instalabel/client/exceptions.py
instalabel/client/py.typed
instalabel/client/rest.py
instalabel/client/api/__init__.py
instalabel/client/api/auth_api.py
instalabel/client/api/images_api.py
instalabel/client/api/projects_api.py
instalabel/client/models/__init__.py
instalabel/client/models/http_validation_error.py
instalabel/client/models/image_response.py
instalabel/client/models/project_create.py
instalabel/client/models/project_response.py
instalabel/client/models/project_update_request.py
instalabel/client/models/task_enum.py
instalabel/client/models/token.py
instalabel/client/models/validation_error.py
instalabel/client/models/validation_error_loc_inner.py
InstaLabelClient-0.0.4.dist-info/METADATA
InstaLabelClient-0.0.4.dist-info/WHEEL
InstaLabelClient-0.0.4.dist-info/top_level.txt
InstaLabelClient-0.0.4.dist-info/RECORD
