Metadata-Version: 2.1
Name: InstaLabelClient
Version: 0.0.4
Summary: FastAPI
Home-page: 
Author: InstaLabel Inc.
Author-email: aadil@instalabel.ai
Keywords: InstaLabel
Requires-Dist: urllib3 <2.1.0,>=1.25.3
Requires-Dist: python-dateutil
Requires-Dist: pydantic >=2
Requires-Dist: typing-extensions >=4.7.1
Requires-Dist: tqdm >=4.66.4
